poscolp/__init__.py
poscolp/__version__.py
posco_lp-1.1.3.dist-info/LICENSE.txt
posco_lp-1.1.3.dist-info/METADATA
posco_lp-1.1.3.dist-info/WHEEL
posco_lp-1.1.3.dist-info/top_level.txt
posco_lp-1.1.3.dist-info/RECORD
