Metadata-Version: 2.1
Name: posco-lp
Version: 1.1.3
Summary: POSCO Learning Platform Crawling Code Library
Home-page: https://github.com/hrdkdh
Author: Duhwan Kim
Author-email: hrdkdh@naver.com
License: UNKNOWN
Project-URL: Bug Tracker, https://github.com/hrdkdh
Keywords: POSCO,learning platform,lp
Platform: UNKNOWN
Classifier: Programming Language :: Python :: 3
Classifier: License :: OSI Approved :: MIT License
Classifier: Operating System :: OS Independent
Requires-Python: >=3.6
License-File: LICENSE.txt
Requires-Dist: requests
Requires-Dist: urllib3
Requires-Dist: numpy
Requires-Dist: pandas
Requires-Dist: pyautogui
Requires-Dist: bs4
